.DS_Store
test_pkg1/__init__.py
test_pkg1/_version.py
test_pkg1/_version_old.py
test_pkg1/cli.py
test_pkg1/test_pkg1.py
test_pkg1-0.1.0.8.dist-info/DESCRIPTION.rst
test_pkg1-0.1.0.8.dist-info/METADATA
test_pkg1-0.1.0.8.dist-info/RECORD
test_pkg1-0.1.0.8.dist-info/WHEEL
test_pkg1-0.1.0.8.dist-info/entry_points.txt
test_pkg1-0.1.0.8.dist-info/metadata.json
test_pkg1-0.1.0.8.dist-info/top_level.txt
