Metadata-Version: 2.0
Name: test-pkg1
Version: 0.1.0.8
Summary: Testing cookiecutter
Home-page: https://github.com/limitlessv/test_pkg1
Author: Shmuel Maruani
Author-email: shmuel@limitlessv.com
License: UNKNOWN
Keywords: test_pkg1
Platform: UNKNOWN
Classifier: Development Status :: 2 - Pre-Alpha
Classifier: Intended Audience :: Developers
Classifier: Natural Language :: English
Classifier: Programming Language :: Python :: 2
Classifier: Programming Language :: Python :: 2.6
Classifier: Programming Language :: Python :: 2.7
Classifier: Programming Language :: Python :: 3
Classifier: Programming Language :: Python :: 3.3
Classifier: Programming Language :: Python :: 3.4
Classifier: Programming Language :: Python :: 3.5
Classifier: Programming Language :: Python :: 3.6
Requires-Dist: Click (>=6.0)
